Metadata-Version: 1.0
Name: objectinator
Version: 0.0.1
Summary: Python packege to help navigate between dictionaries, tuples, lists, sets and object classes
Home-page: UNKNOWN
Author: Mike Zinyoni
Author-email: mzinyoni7@outlook.com
License: UNKNOWN
Keywords: Objects,Lists,Dictionaries,Tuples
Platform: UNKNOWN
